tee_subprocess-1.2.0.dist-info/METADATA
tee_subprocess-1.2.0.dist-info/WHEEL
tee_subprocess-1.2.0.dist-info/entry_points.txt
tee_subprocess-1.2.0.dist-info/licenses/LICENSE
tee_subprocess/__init__.py
tee_subprocess/py.typed
tee_subprocess/subprocess.py
tee_subprocess-1.2.0.dist-info/RECORD
