Metadata-Version: 2.1
Name: tee-subprocess
Version: 1.2.0
Summary: A subprocess replacement with tee support for both synchronous and asynchronous contexts.
Author-Email: Elias Gabriel <me@eliasfgabriel.com>
License: MIT
Project-URL: documentation, https://github.com/thearchitector/tee-subprocess
Project-URL: repository, https://github.com/thearchitector/tee-subprocess
Project-URL: changelog, https://github.com/thearchitector/tee-subprocess/blob/main/CHANGELOG.md
Requires-Python: >=3.8
